aiida_crystal17/__init__.py
aiida_crystal17/calcfunctions/__init__.py
aiida_crystal17/calcfunctions/band_gap.py
aiida_crystal17/calculations/__init__.py
aiida_crystal17/calculations/cry_abstract.py
aiida_crystal17/calculations/cry_basic.py
aiida_crystal17/calculations/cry_main.py
aiida_crystal17/calculations/prop_abstract.py
aiida_crystal17/calculations/prop_doss.py
aiida_crystal17/calculations/prop_ech3.py
aiida_crystal17/calculations/prop_newk.py
aiida_crystal17/calculations/prop_ppan.py
aiida_crystal17/cmndline/__init__.py
aiida_crystal17/cmndline/basis_set.py
aiida_crystal17/cmndline/cmd_parser.py
aiida_crystal17/cmndline/options.py
aiida_crystal17/cmndline/symmetry.py
aiida_crystal17/common/__init__.py
aiida_crystal17/common/atoms.py
aiida_crystal17/common/dict_funcs.py
aiida_crystal17/common/kpoints.py
aiida_crystal17/common/mapping.py
aiida_crystal17/common/parsing.py
aiida_crystal17/data/__init__.py
aiida_crystal17/data/basis_set.py
aiida_crystal17/data/gcube.py
aiida_crystal17/data/input_params.py
aiida_crystal17/data/kinds.py
aiida_crystal17/data/symmetry.py
aiida_crystal17/immigration/__init__.py
aiida_crystal17/immigration/create_calcjob.py
aiida_crystal17/immigration/create_inputs.py
aiida_crystal17/parsers/__init__.py
aiida_crystal17/parsers/cry_doss.py
aiida_crystal17/parsers/cry_ech3.py
aiida_crystal17/parsers/cry_main.py
aiida_crystal17/parsers/cry_newk.py
aiida_crystal17/parsers/cry_ppan.py
aiida_crystal17/parsers/raw/__init__.py
aiida_crystal17/parsers/raw/crystal_fort25.py
aiida_crystal17/parsers/raw/crystal_fort9.py
aiida_crystal17/parsers/raw/crystal_ppan.py
aiida_crystal17/parsers/raw/crystal_stdout.py
aiida_crystal17/parsers/raw/doss_input.py
aiida_crystal17/parsers/raw/gaussian_cube.py
aiida_crystal17/parsers/raw/inputd12_read.py
aiida_crystal17/parsers/raw/inputd12_write.py
aiida_crystal17/parsers/raw/main_out.py
aiida_crystal17/parsers/raw/parse_bases.py
aiida_crystal17/parsers/raw/parse_fort34.py
aiida_crystal17/parsers/raw/pbs.py
aiida_crystal17-0.11.0.dist-info/LICENSE
aiida_crystal17-0.11.0.dist-info/METADATA
aiida_crystal17-0.11.0.dist-info/WHEEL
aiida_crystal17-0.11.0.dist-info/entry_points.txt
aiida_crystal17-0.11.0.dist-info/top_level.txt
aiida_crystal17-0.11.0.dist-info/RECORD
