Metadata-Version: 2.1
Name: aiida-crystal17
Version: 0.11.0
Summary: AiiDA plugin for running the CRYSTAL17 code
Home-page: https://github.com/chrisjsewell/aiida-crystal17
Author: Chris Sewell
Author-email: chrisj_sewell@hotmail.com
License: MIT
Platform: UNKNOWN
Classifier: Programming Language :: Python
Classifier: Programming Language :: Python :: 2.7
Classifier: Programming Language :: Python :: 3.6
Classifier: Topic :: Scientific/Engineering :: Chemistry
Classifier: Topic :: Scientific/Engineering :: Physics
Classifier: Framework :: AiiDA
Requires-Python: >=3.6
Requires-Dist: aiida-core (<2.0.0,>=1.4.0)
Requires-Dist: pyyaml
Requires-Dist: jsonextended (>=0.7.10)
Requires-Dist: jsonschema
Requires-Dist: spglib (<2.0.0,>=1.10.0)
Requires-Dist: ase (<4.0.0,>=3.12.0)
Requires-Dist: PyCifRW (<5.0.0,>=4.4.1)
Requires-Dist: importlib-resources
Provides-Extra: code_style
Requires-Dist: pre-commit (~=2.6) ; extra == 'code_style'
Provides-Extra: docs
Requires-Dist: myst-nb (~=0.10.1) ; extra == 'docs'
Requires-Dist: sphinx-book-theme ; extra == 'docs'
Provides-Extra: testing
Requires-Dist: pgtest ; extra == 'testing'
Requires-Dist: pytest ; extra == 'testing'
Requires-Dist: coverage ; extra == 'testing'
Requires-Dist: pytest-cov ; extra == 'testing'
Requires-Dist: pytest-timeout ; extra == 'testing'
Requires-Dist: pytest-regressions ; extra == 'testing'
Requires-Dist: pytest-notebook ; extra == 'testing'
